Metadata-Version: 2.1
Name: mikrtoik-bt5
Version: 0.0.1
Summary: MikroTik BT5 scanner
Home-page: https://github.com/Anrijs/MikroTik-BT5-Python
License: UNKNOWN
Platform: UNKNOWN
Classifier: Programming Language :: Python
Classifier: Programming Language :: Python :: 3
Classifier: License :: OSI Approved :: MIT License
Classifier: Operating System :: OS Independent
